[ {
  "title" : "book 0",
  "authorName" : "author 0",
  "bookID" : 0,
  "pages" : 10,
  "authorID" : 0
}, {
  "title" : "book 1",
  "authorName" : "author 1",
  "bookID" : 1,
  "pages" : 11,
  "authorID" : 1
}, {
  "title" : "book 2",
  "authorName" : "author 2",
  "bookID" : 2,
  "pages" : 12,
  "authorID" : 2
}, {
  "title" : "book 3",
  "authorName" : "author 3",
  "bookID" : 3,
  "pages" : 13,
  "authorID" : 3
}, {
  "title" : "book 4",
  "authorName" : "author 4",
  "bookID" : 4,
  "pages" : 14,
  "authorID" : 4
} ]